README.md
setup.py
skipq/__init__.py
skipq/__main__.py
skipq.egg-info/PKG-INFO
skipq.egg-info/SOURCES.txt
skipq.egg-info/dependency_links.txt
skipq.egg-info/not-zip-safe
skipq.egg-info/requires.txt
skipq.egg-info/top_level.txt