Metadata-Version: 1.0
Name: skipq
Version: 0.1.2
Summary: Makes our life easy by clicking Skip button with just pressing Enter.
Home-page: https://github.com/anilkumarvvss/skipq
Author: anilkumarvvss
Author-email: vvssak1023@gmail.com
License: GNU General Public License
Keywords: chegg skip question automation vvss
Platform: UNKNOWN
